{"ProductId": "564790", "ETag": "a9d0c5a9cc28bbdeea4c3b8588436dbcfc6fb6ec2af8e6fa771be6142e0b2e11", "ProductName": "DuoPower ETA 8 x 40 Sicherheitsschraube", "Slug": "/standardbefestigungen/kunststoffduebel/duopower-eta/564790-duopower-eta-8-x-40-sicherheitsschraube", "ParentCategory": "1595947316769453", "ParentCategoryList": ["1595947316769453"], "RootCategory": "1001341446", "CategoryPath": ["1001341446", "1001341448", "1595947316769453"], "Media": [{"DocumentId": "4c54059535d836e041123b37e214ee0a", "Url": "https://media.fischer.group/v7/_pim-media-prod_/Product%20Pictures/Product%20Pictures%20fischer/W1_P_P_DUEBELSCHRAUBE-6KT-DUOPOWER-CGI_V1.jpg", "Filename": "W1_P_P_DUEBELSCHRAUBE-6KT-DUOPOWER-CGI_V1.jpg", "NameConvention": "P_P_F", "OutputType": "PR", "Format": "jpg", "FileSize": 847539, "Type": "Product Picture", "Position": 1, "TextList": [{"Key": "BILDLEG_NEXMART", "Value": "Produktbild"}, {"Key": "KAT_NEU_PRODBILD", "Value": "Produktbild"}]}, {"DocumentId": "5f5a41b3185712cb4bde2d9b88b9bfce", "Url": "https://media.fischer.group/v7/_pim-media-prod_/Product%20Pictures/Product%20Pictures%20fischer/W1_P_P_DUEBELSCHRAUBE-6KT-DUOPOWER-CGI_V1.jpg?w=1000&h=1000&func=fit&bg_colour=white", "Filename": "W1_P_P_DUEBELSCHRAUBE-6KT-DUOPOWER-CGI_V1.jpg", "NameConvention": "P_P_F", "OutputType": "PP", "Format": "jpg", "FileSize": 847539, "Type": "Product Picture", "Position": 1, "TextList": [{"Key": "BILDLEG_NEXMART", "Value": "Produktbild"}, {"Key": "KAT_NEU_PRODBILD", "Value": "Produktbild"}]}, {"DocumentId": "b4158c5a7484c666f9f803388af5c272", "Url": "https://media.fischer.group/v7/_pim-media-prod_/Product%20Pictures/Product%20Pictures%20fischer/W1_P_P_DUEBELSCHRAUBE-6KT-DUOPOWER-CGI_V1.jpg?w=300&h=300&func=fit&bg_colour=white", "Filename": "W1_P_P_DUEBELSCHRAUBE-6KT-DUOPOWER-CGI_V1.jpg", "NameConvention": "P_P_F", "OutputType": "IS", "Format": "jpg", "FileSize": 847539, "Type": "Product Picture", "Position": 1, "TextList": [{"Key": "BILDLEG_NEXMART", "Value": "Produktbild"}, {"Key": "KAT_NEU_PRODBILD", "Value": "Produktbild"}]}, {"DocumentId": "5c92c524d97d4d8c9ce945f1679e2907", "Url": "https://media.fischer.group/v7/_pim-media-prod_/Application%20Pictures/Application%20Pictures%20CGI%20new%20CD/W1_A_I_04_KONSOLE_SALL_AQQ_V1.jpg", "Filename": "W1_A_I_04_KONSOLE_SALL_AQQ_V1.jpg", "NameConvention": "A_I_01", "OutputType": "PR", "Format": "jpg", "FileSize": 3122326, "Type": "Application Picture", "Position": 1, "TextList": [{"Key": "BILDLEG_NEXMART", "Value": "Anwendungsbild"}, {"Key": "KAT_NEU_PRODBILD", "Value": "Anwendungsbild"}]}, {"DocumentId": "f189cf3679907f9bc3601aa813ae8c57", "Url": "https://media.fischer.group/v7/_pim-media-prod_/Application%20Pictures/Application%20Pictures%20CGI%20new%20CD/W1_A_I_04_KONSOLE_SALL_AQQ_V1.jpg?w=1250&bg_colour=white", "Filename": "W1_A_I_04_KONSOLE_SALL_AQQ_V1.jpg", "NameConvention": "A_I_01", "OutputType": "PP", "Format": "jpg", "FileSize": 3122326, "Type": "Application Picture", "Position": 1, "TextList": [{"Key": "BILDLEG_NEXMART", "Value": "Anwendungsbild"}, {"Key": "KAT_NEU_PRODBILD", "Value": "Anwendungsbild"}]}, {"DocumentId": "4d6f4eb583016f20fb93c7073ae9dfd6", "Url": "https://media.fischer.group/v7/_pim-media-prod_/Application%20Pictures/Application%20Pictures%20CGI%20new%20CD/W1_A_I_04_509-ROHRE-DUOPOWER-V2.jpg", "Filename": "W1_A_I_04_509-ROHRE-DUOPOWER-V2.jpg", "NameConvention": "A_I_01", "OutputType": "PR", "Format": "jpg", "FileSize": 2543526, "Type": "Application Picture", "Position": 2, "TextList": [{"Key": "BILDLEG_NEXMART", "Value": "Anwendungsbild"}, {"Key": "KAT_NEU_PRODBILD", "Value": "Anwendungsbild"}]}, {"DocumentId": "bc8729aad21bdea0d68387a434785a96", "Url": "https://media.fischer.group/v7/_pim-media-prod_/Application%20Pictures/Application%20Pictures%20CGI%20new%20CD/W1_A_I_04_509-ROHRE-DUOPOWER-V2.jpg?w=1250&bg_colour=white", "Filename": "W1_A_I_04_509-ROHRE-DUOPOWER-V2.jpg", "NameConvention": "A_I_01", "OutputType": "PP", "Format": "jpg", "FileSize": 2543526, "Type": "Application Picture", "Position": 2, "TextList": [{"Key": "BILDLEG_NEXMART", "Value": "Anwendungsbild"}, {"Key": "KAT_NEU_PRODBILD", "Value": "Anwendungsbild"}]}, {"DocumentId": "a6e5b3e03704faabace0f00fab2e0f39", "Url": "https://media.fischer.group/v7/_pim-media-prod_/Logos_Icons/Product%20Features%20new%20CD/W1_L_ETA-FLAG_RGB_N_SALL_AQQ_V1.jpg", "Filename": "W1_L_ETA-FLAG_RGB_N_SALL_AQQ_V1.jpg", "NameConvention": "L_N", "OutputType": "PR", "Format": "jpg", "FileSize": 77861, "Type": "Logo", "Position": 1, "TextList": [{"Key": "BILDLEG_NEXMART", "Value": "Logo"}, {"Key": "KAT_NEU_PRODBILD", "Value": "Logo"}]}, {"DocumentId": "edefedb9f031845f94332d96507ffeff", "Url": "https://media.fischer.group/v7/_pim-media-prod_/Logos_Icons/Product%20Features%20new%20CD/W1_L_ETA-FLAG_RGB_N_SALL_AQQ_V1.jpg?w=250&func=fit&bg_colour=white", "Filename": "W1_L_ETA-FLAG_RGB_N_SALL_AQQ_V1.jpg", "NameConvention": "L_N", "OutputType": "PP", "Format": "jpg", "FileSize": 77861, "Type": "Logo", "Position": 1, "TextList": [{"Key": "BILDLEG_NEXMART", "Value": "Logo"}, {"Key": "KAT_NEU_PRODBILD", "Value": "Logo"}]}, {"DocumentId": "a6e5b3e03704faabace0f00fab2e0f39", "Url": "https://media.fischer.group/v7/_pim-media-prod_/Logos_Icons/Product%20Features%20new%20CD/W1_L_ETA-FLAG_RGB_N_SALL_AQQ_V1.jpg", "Filename": "W1_L_ETA-FLAG_RGB_N_SALL_AQQ_V1.jpg", "NameConvention": "L_N", "OutputType": "PR", "Format": "jpg", "FileSize": 77861, "Type": "Logo", "Position": 1, "TextList": [{"Key": "BILDLEG_NEXMART", "Value": "Logo"}, {"Key": "KAT_NEU_PRODBILD", "Value": "Logo"}]}, {"DocumentId": "edefedb9f031845f94332d96507ffeff", "Url": "https://media.fischer.group/v7/_pim-media-prod_/Logos_Icons/Product%20Features%20new%20CD/W1_L_ETA-FLAG_RGB_N_SALL_AQQ_V1.jpg?w=250&func=fit&bg_colour=white", "Filename": "W1_L_ETA-FLAG_RGB_N_SALL_AQQ_V1.jpg", "NameConvention": "L_N", "OutputType": "PP", "Format": "jpg", "FileSize": 77861, "Type": "Logo", "Position": 1, "TextList": [{"Key": "BILDLEG_NEXMART", "Value": "Logo"}, {"Key": "KAT_NEU_PRODBILD", "Value": "Logo"}]}, {"DocumentId": "72e8c51cdf45190f57bc09ca28e3199e", "Description": "TnG6-vezfMg", "Url": "https://media.fischer.group/v7/_pim-media-prod_/Movies/fischer%20Videos%20placeholder%20pictures/MOV_DUOPOWER_DE_V1.jpg", "Language": "DE", "Filename": "MOV_DUOPOWER_DE_V1.jpg", "NameConvention": "MOV", "OutputType": "IS", "Format": "jpg", "FileSize": 57099, "Type": "Video", "Position": 1, "TextList": [{"Key": "INFO1", "Value": "TnG6-vezfMg"}, {"Key": "BILDLEG_NEXMART", "Value": "Video"}, {"Key": "KAT_NEU_PRODBILD", "Value": "Video"}]}, {"DocumentId": "5253bc700035d1c2abbaf1f4016d5c7e", "Url": "https://media.fischer.group/v7/_pim-media-prod_/Logos_Icons/NEUTRAL/W1_ZI_ETA_ETA-ALLG-NEUTRAL_N_SALL_AQQ_V4.jpg", "Filename": "W1_ZI_ETA_ETA-ALLG-NEUTRAL_N_SALL_AQQ_V4.jpg", "NameConvention": "ZI_Z_01_N", "OutputType": "PP", "Format": "jpg", "FileSize": 7581, "Type": "Icon", "Position": 1, "TextList": [{"Key": "BILDLEG_NEXMART", "Value": "Icon"}, {"Key": "KAT_NEU_PRODBILD", "Value": "Icon"}]}, {"DocumentId": "5253bc700035d1c2abbaf1f4016d5c7e", "Url": "https://media.fischer.group/v7/_pim-media-prod_/Logos_Icons/NEUTRAL/W1_ZI_ETA_ETA-ALLG-NEUTRAL_N_SALL_AQQ_V4.jpg", "Filename": "W1_ZI_ETA_ETA-ALLG-NEUTRAL_N_SALL_AQQ_V4.jpg", "NameConvention": "ZI_Z_01_N", "OutputType": "PR", "Format": "jpg", "FileSize": 7581, "Type": "Icon", "Position": 1, "TextList": [{"Key": "BILDLEG_NEXMART", "Value": "Icon"}, {"Key": "KAT_NEU_PRODBILD", "Value": "Icon"}]}, {"DocumentId": "6f9daf5096f9d8a6f87a33fe4fa6405d", "Url": "https://media.fischer.group/v7/_pim-media-prod_/Logos_Icons/NEUTRAL/W1_ZI_A_01_DOP_N_SALL_AQQ_V1.jpg", "Filename": "W1_ZI_A_01_DOP_N_SALL_AQQ_V1.jpg", "NameConvention": "ZI_Z_01_N", "OutputType": "PP", "Format": "jpg", "FileSize": 66293, "Type": "Icon", "Position": 3, "TextList": [{"Key": "BILDLEG_NEXMART", "Value": "Icon"}, {"Key": "KAT_NEU_PRODBILD", "Value": "Icon"}]}, {"DocumentId": "6f9daf5096f9d8a6f87a33fe4fa6405d", "Url": "https://media.fischer.group/v7/_pim-media-prod_/Logos_Icons/NEUTRAL/W1_ZI_A_01_DOP_N_SALL_AQQ_V1.jpg", "Filename": "W1_ZI_A_01_DOP_N_SALL_AQQ_V1.jpg", "NameConvention": "ZI_Z_01_N", "OutputType": "PR", "Format": "jpg", "FileSize": 66293, "Type": "Icon", "Position": 3, "TextList": [{"Key": "BILDLEG_NEXMART", "Value": "Icon"}, {"Key": "KAT_NEU_PRODBILD", "Value": "Icon"}]}], "AssemblyMedia": [{"Name": "Mounting Strip 1 Picture", "Media": [{"DocumentId": "b66235c1f836cecc9156f1daa5a1c536", "Url": "https://media.fischer.group/v7/_pim-media-prod_/Mounting%20Pictures/Mounting%20Pictures%20NEW/fischer/W6_M_L_01_DUO-VOLL-BETON-SS.jpg", "Filename": "W6_M_L_01_DUO-VOLL-BETON-SS.jpg", "NameConvention": "M_G_01_F", "OutputType": "PR", "Format": "jpg", "FileSize": 136929, "Type": "Mounting Strip 1 Picture", "Position": 1, "TextList": [{"Key": "BILDLEG_NEXMART", "Value": "Montagebild"}, {"Key": "KAT_NEU_PRODBILD", "Value": "Montagebild"}]}, {"DocumentId": "0ed6d1e5f4d88236831dbb8ff1a81b10", "Url": "https://media.fischer.group/v7/_pim-media-prod_/Mounting%20Pictures/Mounting%20Pictures%20NEW/fischer/W6_M_L_01_DUO-VOLL-BETON-SS.jpg?w=276&h=210&func=fit&bg_colour=white", "Filename": "W6_M_L_01_DUO-VOLL-BETON-SS.jpg", "NameConvention": "M_G_01_F", "OutputType": "PP", "Format": "jpg", "FileSize": 136929, "Type": "Mounting Strip 1 Picture", "Position": 1, "TextList": [{"Key": "BILDLEG_NEXMART", "Value": "Montagebild"}, {"Key": "KAT_NEU_PRODBILD", "Value": "Montagebild"}]}, {"DocumentId": "eb37d76eb37df06940e5e2481c79c4f9", "Url": "https://media.fischer.group/v7/_pim-media-prod_/Mounting%20Pictures/Mounting%20Pictures%20NEW/fischer/W6_M_L_02_DUO-VOLL-BETON-SS.jpg", "Filename": "W6_M_L_02_DUO-VOLL-BETON-SS.jpg", "NameConvention": "M_G_01_F", "OutputType": "PR", "Format": "jpg", "FileSize": 137047, "Type": "Mounting Strip 1 Picture", "Position": 2, "TextList": [{"Key": "BILDLEG_NEXMART", "Value": "Montagebild"}, {"Key": "KAT_NEU_PRODBILD", "Value": "Montagebild"}]}, {"DocumentId": "0ecb75490cffc800e65c9ec532eea9bc", "Url": "https://media.fischer.group/v7/_pim-media-prod_/Mounting%20Pictures/Mounting%20Pictures%20NEW/fischer/W6_M_L_02_DUO-VOLL-BETON-SS.jpg?w=276&h=210&func=fit&bg_colour=white", "Filename": "W6_M_L_02_DUO-VOLL-BETON-SS.jpg", "NameConvention": "M_G_01_F", "OutputType": "PP", "Format": "jpg", "FileSize": 137047, "Type": "Mounting Strip 1 Picture", "Position": 2, "TextList": [{"Key": "BILDLEG_NEXMART", "Value": "Montagebild"}, {"Key": "KAT_NEU_PRODBILD", "Value": "Montagebild"}]}, {"DocumentId": "12fda45375eee1ed99a76d67c1a32c77", "Url": "https://media.fischer.group/v7/_pim-media-prod_/Mounting%20Pictures/Mounting%20Pictures%20NEW/fischer/W6_M_L_03_DUO-VOLL-BETON-SS.jpg", "Filename": "W6_M_L_03_DUO-VOLL-BETON-SS.jpg", "NameConvention": "M_G_01_F", "OutputType": "PR", "Format": "jpg", "FileSize": 141765, "Type": "Mounting Strip 1 Picture", "Position": 3, "TextList": [{"Key": "BILDLEG_NEXMART", "Value": "Montagebild"}, {"Key": "KAT_NEU_PRODBILD", "Value": "Montagebild"}]}, {"DocumentId": "643019b7824f59042facf2ff9d62cd46", "Url": "https://media.fischer.group/v7/_pim-media-prod_/Mounting%20Pictures/Mounting%20Pictures%20NEW/fischer/W6_M_L_03_DUO-VOLL-BETON-SS.jpg?w=276&h=210&func=fit&bg_colour=white", "Filename": "W6_M_L_03_DUO-VOLL-BETON-SS.jpg", "NameConvention": "M_G_01_F", "OutputType": "PP", "Format": "jpg", "FileSize": 141765, "Type": "Mounting Strip 1 Picture", "Position": 3, "TextList": [{"Key": "BILDLEG_NEXMART", "Value": "Montagebild"}, {"Key": "KAT_NEU_PRODBILD", "Value": "Montagebild"}]}, {"DocumentId": "e7641d74bd88fc547cbdddbed59a83d3", "Url": "https://media.fischer.group/v7/_pim-media-prod_/Mounting%20Pictures/Mounting%20Pictures%20NEW/fischer/W6_M_L_04_DUO-VOLL-BETON-SS.jpg", "Filename": "W6_M_L_04_DUO-VOLL-BETON-SS.jpg", "NameConvention": "M_G_01_F", "OutputType": "PR", "Format": "jpg", "FileSize": 137841, "Type": "Mounting Strip 1 Picture", "Position": 4, "TextList": [{"Key": "BILDLEG_NEXMART", "Value": "Montagebild"}, {"Key": "KAT_NEU_PRODBILD", "Value": "Montagebild"}]}, {"DocumentId": "a620e19ba6e3bad0a7f8639de13c2660", "Url": "https://media.fischer.group/v7/_pim-media-prod_/Mounting%20Pictures/Mounting%20Pictures%20NEW/fischer/W6_M_L_04_DUO-VOLL-BETON-SS.jpg?w=276&h=210&func=fit&bg_colour=white", "Filename": "W6_M_L_04_DUO-VOLL-BETON-SS.jpg", "NameConvention": "M_G_01_F", "OutputType": "PP", "Format": "jpg", "FileSize": 137841, "Type": "Mounting Strip 1 Picture", "Position": 4, "TextList": [{"Key": "BILDLEG_NEXMART", "Value": "Montagebild"}, {"Key": "KAT_NEU_PRODBILD", "Value": "Montagebild"}]}]}, {"Name": "Mounting Strip 2 Picture", "Media": [{"DocumentId": "3b8ab8ec6d17712d3edc4492991b95f9", "Url": "https://media.fischer.group/v7/_pim-media-prod_/Mounting%20Pictures/Mounting%20Pictures%20NEW/fischer/W6_M_L_01_DUO-VOLL-LOCH-SS.jpg", "Filename": "W6_M_L_01_DUO-VOLL-LOCH-SS.jpg", "NameConvention": "M_G_02_F", "OutputType": "PR", "Format": "jpg", "FileSize": 81127, "Type": "Mounting Strip 2 Picture", "Position": 1, "TextList": [{"Key": "BILDLEG_NEXMART", "Value": "Montagebild"}, {"Key": "KAT_NEU_PRODBILD", "Value": "Montagebild"}]}, {"DocumentId": "ba1717f66bc5d538e98132c3e7293eb8", "Url": "https://media.fischer.group/v7/_pim-media-prod_/Mounting%20Pictures/Mounting%20Pictures%20NEW/fischer/W6_M_L_01_DUO-VOLL-LOCH-SS.jpg?w=276&h=210&func=fit&bg_colour=white", "Filename": "W6_M_L_01_DUO-VOLL-LOCH-SS.jpg", "NameConvention": "M_G_02_F", "OutputType": "PP", "Format": "jpg", "FileSize": 81127, "Type": "Mounting Strip 2 Picture", "Position": 1, "TextList": [{"Key": "BILDLEG_NEXMART", "Value": "Montagebild"}, {"Key": "KAT_NEU_PRODBILD", "Value": "Montagebild"}]}, {"DocumentId": "80f7deb31f731d19a9469d1b53a0f8a3", "Url": "https://media.fischer.group/v7/_pim-media-prod_/Mounting%20Pictures/Mounting%20Pictures%20NEW/fischer/W6_M_L_02_DUO-VOLL-LOCH-SS.jpg", "Filename": "W6_M_L_02_DUO-VOLL-LOCH-SS.jpg", "NameConvention": "M_G_02_F", "OutputType": "PR", "Format": "jpg", "FileSize": 143630, "Type": "Mounting Strip 2 Picture", "Position": 2, "TextList": [{"Key": "BILDLEG_NEXMART", "Value": "Montagebild"}, {"Key": "KAT_NEU_PRODBILD", "Value": "Montagebild"}]}, {"DocumentId": "da2e8d5ae712158fb1f47a3666b704a5", "Url": "https://media.fischer.group/v7/_pim-media-prod_/Mounting%20Pictures/Mounting%20Pictures%20NEW/fischer/W6_M_L_02_DUO-VOLL-LOCH-SS.jpg?w=276&h=210&func=fit&bg_colour=white", "Filename": "W6_M_L_02_DUO-VOLL-LOCH-SS.jpg", "NameConvention": "M_G_02_F", "OutputType": "PP", "Format": "jpg", "FileSize": 143630, "Type": "Mounting Strip 2 Picture", "Position": 2, "TextList": [{"Key": "BILDLEG_NEXMART", "Value": "Montagebild"}, {"Key": "KAT_NEU_PRODBILD", "Value": "Montagebild"}]}, {"DocumentId": "8fae1257aac4bc92f0b66c636dc20ce7", "Url": "https://media.fischer.group/v7/_pim-media-prod_/Mounting%20Pictures/Mounting%20Pictures%20NEW/fischer/W6_M_L_03_DUO-VOLL-LOCH-SS.jpg", "Filename": "W6_M_L_03_DUO-VOLL-LOCH-SS.jpg", "NameConvention": "M_G_02_F", "OutputType": "PR", "Format": "jpg", "FileSize": 81652, "Type": "Mounting Strip 2 Picture", "Position": 3, "TextList": [{"Key": "BILDLEG_NEXMART", "Value": "Montagebild"}, {"Key": "KAT_NEU_PRODBILD", "Value": "Montagebild"}]}, {"DocumentId": "295ad81a0f91e3c54cf98ee09fca8050", "Url": "https://media.fischer.group/v7/_pim-media-prod_/Mounting%20Pictures/Mounting%20Pictures%20NEW/fischer/W6_M_L_03_DUO-VOLL-LOCH-SS.jpg?w=276&h=210&func=fit&bg_colour=white", "Filename": "W6_M_L_03_DUO-VOLL-LOCH-SS.jpg", "NameConvention": "M_G_02_F", "OutputType": "PP", "Format": "jpg", "FileSize": 81652, "Type": "Mounting Strip 2 Picture", "Position": 3, "TextList": [{"Key": "BILDLEG_NEXMART", "Value": "Montagebild"}, {"Key": "KAT_NEU_PRODBILD", "Value": "Montagebild"}]}, {"DocumentId": "7139ad97615e4b32949a75f046fec264", "Url": "https://media.fischer.group/v7/_pim-media-prod_/Mounting%20Pictures/Mounting%20Pictures%20NEW/fischer/W6_M_L_04_DUO-VOLL-LOCH-SS.jpg", "Filename": "W6_M_L_04_DUO-VOLL-LOCH-SS.jpg", "NameConvention": "M_G_02_F", "OutputType": "PR", "Format": "jpg", "FileSize": 146893, "Type": "Mounting Strip 2 Picture", "Position": 4, "TextList": [{"Key": "BILDLEG_NEXMART", "Value": "Montagebild"}, {"Key": "KAT_NEU_PRODBILD", "Value": "Montagebild"}]}, {"DocumentId": "a959d2e8d1721924cfc30ef43727b6e3", "Url": "https://media.fischer.group/v7/_pim-media-prod_/Mounting%20Pictures/Mounting%20Pictures%20NEW/fischer/W6_M_L_04_DUO-VOLL-LOCH-SS.jpg?w=276&h=210&func=fit&bg_colour=white", "Filename": "W6_M_L_04_DUO-VOLL-LOCH-SS.jpg", "NameConvention": "M_G_02_F", "OutputType": "PP", "Format": "jpg", "FileSize": 146893, "Type": "Mounting Strip 2 Picture", "Position": 4, "TextList": [{"Key": "BILDLEG_NEXMART", "Value": "Montagebild"}, {"Key": "KAT_NEU_PRODBILD", "Value": "Montagebild"}]}]}], "Documents": {"AdditionalDocuments": [{"DocumentId": "ddb334664388d78949041d99b7c679df", "Name": "Lastentabelle", "Url": "https://fiproductmedia.azureedge.net/media/Load%20Tables/Load%20Tables%20fischer/LT_01-DUOPOWER-ETA-DE.pdf", "Language": "DE", "Filename": "LT_01-DUOPOWER-ETA-DE.pdf", "NameConvention": "LT_01_F", "OutputType": "IP", "Format": "pdf", "FileSize": 54992, "Type": "Load Table", "Position": 1, "TextList": [{"Key": "BILDLEG_NEXMART", "Value": "Lastentabelle"}, {"Key": "KAT_NEU_PRODBILD", "Value": "Lastentabelle"}], "CharacteristicValueNames": ["Lastentabelle"]}], "Approvals": [{"DocumentId": "06e676befa0779c6fa7af466d31bead0", "Name": "ETA - Europ\u00e4ische Technische Bewertung", "Description": "Europ\u00e4ische Technische Bewertung f\u00fcr fischer Universald\u00fcbel DuoPower ETA - Kunstoffd\u00fcbel f\u00fcr redundante nichttragende Systeme in Beton und Mauerwerk", "Url": "https://fiproductmedia.azureedge.net/media/Certification%20Documents/ETA%20European%20Technical%20Assessment/fischer/ZD_ETAB_22-0512_DE_V1.pdf", "Language": "DE", "Filename": "ZD_ETAB_22-0512_DE_V1.pdf", "NameConvention": "ZD_ETAB_F", "OutputType": "IP", "ValidFrom": "2022-11-04T00:00:00", "Format": "pdf", "FileSize": 734656, "Type": "ETA - European Technical Assessment", "Position": 1, "TextList": [{"Key": "INFO1", "Value": "Europ\u00e4ische Technische Bewertung f\u00fcr fischer Universald\u00fcbel DuoPower ETA - Kunstoffd\u00fcbel f\u00fcr redundante nichttragende Systeme in Beton und Mauerwerk"}], "AttributeList": [{"Name": "Zulassungsnummer", "Value": "ETA-22/0512", "Key": "ZULANR"}], "CharacteristicValueNames": ["ETA - Europ\u00e4ische Technische Bewertung"], "ChildDocumentIds": ["5236dbf0efa7b9dc6b67953f6b79c314"]}, {"DocumentId": "5236dbf0efa7b9dc6b67953f6b79c314", "Name": "DOP - Declaration of Performance", "Description": "Leistungserkl\u00e4rung f\u00fcr fischer Universald\u00fcbel DuoPower ETA (Kunststoffd\u00fcbel f\u00fcr die Verwendung in Beton und Mauerwerk)", "Url": "https://fiproductmedia.azureedge.net/media/Certification%20Documents/DOP%20Documents/fischer/ZD_DOP_DE_DUOPOWER_DOP-0323_ETA-22-0512.pdf", "Language": "DE", "Filename": "ZD_DOP_DE_DUOPOWER_DOP-0323_ETA-22-0512.pdf", "NameConvention": "ZD_DOP_F", "OutputType": "IP", "ValidFrom": "2022-11-24T00:00:00", "Format": "pdf", "FileSize": 934420, "Type": "DOP - Declaration of Performance", "Position": 2, "TextList": [{"Key": "INFO1", "Value": "Leistungserkl\u00e4rung f\u00fcr fischer Universald\u00fcbel DuoPower ETA (Kunststoffd\u00fcbel f\u00fcr die Verwendung in Beton und Mauerwerk)"}], "AttributeList": [{"Name": "Zulassungsnummer", "Value": "DoP No. 0323", "Key": "ZULANR"}], "CharacteristicValueNames": ["DOP - Declaration of Performance"], "ParentDocumentId": "06e676befa0779c6fa7af466d31bead0"}]}, "TextList": [{"Key": "BEZEICHNUNG", "Value": "DuoPower ETA 8 x 40 Sicherheitsschraube"}, {"Key": "ARTIKELLANG", "Value": "DuoPower ETA 8 x 40 Sicherheitsschraube"}, {"Key": "ECOMLANG", "Value": "fischer DuoPower ETA 8 x 40 mit Sicherheitsschraube"}, {"Key": "DOKBSTMARKCLAIM", "Value": "Das Duo aus Power und Schlauer"}, {"Key": "DOKBSTMARKDESCR", "Value": "Der fischer DuoPower ist ein intelligenter 2-Komponenten-D\u00fcbel mit drei Funktionsprinzipien. Der intelligente Universald\u00fcbel ist f\u00fcr Befestigungen in allen Baustoffen geeignet. Dies erm\u00f6glicht vielf\u00e4ltige Anwendungen mit nur einem D\u00fcbel. Der fischer DuoPower passt sich selbstst\u00e4ndig dem Baustoff an und leitet durch die drei Funktionsprinzipien klappen, spreizen und knoten h\u00f6chste Lastwerte ein. Die sehr gute R\u00fcckmeldung des D\u00fcbels beim Eindrehen der Schraube schafft ein zus\u00e4tzliches Plus an Sicherheit. Die Europ\u00e4isch Technische Bewertung (ETA) f\u00fcr bestimmte DuoPower Abmessungen garantiert zudem gepr\u00fcfte Sicherheit bei sicherheitsrelevanten Anwendungen in Beton und Mauerwerk (siehe Lasttabelle)."}, {"Key": "KAT_POS", "Value": "<div class=\"h9\">Das Duo aus Power und Schlauer"}, {"Key": "KAT_ANWENDUNG_GEN", "Value": "<div class=\"h10\">Anwendungen</div><ul><li>TV-Konsolen</li><li>Leuchten</li><li>Wandregale</li><li>Spiegelschr\u00e4nke</li><li>Briefkastenanlagen</li><li>Bilder</li><li>Fensterrollos</li><li>Gardinenschienen</li><li>Waschtischbefestigungen</li><li>Sanit\u00e4r/Heizung/Klima-Befestigungen</li><li>Bad- und WC-Einrichtungen</li><li>H\u00e4ngeschr\u00e4nke</li><li>Dunstabzugshauben</li></ul>"}, {"Key": "KAT_BAUSTOFF_GEN", "Value": "<div class=\"h10\">Baustoffe</div><ul><li>Beton</li><li>Vollziegel</li><li>Kalksand-Vollstein</li><li>Porenbeton</li><li>Hochlochziegel</li><li>Kalksand-Lochstein</li><li>Gipsbauplatte</li><li>Gipskarton - und Gipsfaserplatten</li><li>Hohlblock aus Leichtbeton</li><li>Hohldecken aus Ziegel, Beton o. \u00e4.</li><li>Naturstein</li><li>Spanplatten</li><li>Vollgips-Platten</li><li>Vollstein aus Leichtbeton</li></ul>"}, {"Key": "POCTOPFEATURESGEN", "Value": "<div class=\"h10\">Top Features</div><ul><li>Kombination aus zwei Materialkomponenten f\u00fcr mehr Leistung.</li><li>Sichere Funktionen f\u00fcr Voll- (Spreizen) und Loch- und Plattenbaustoffe (Klappen/Knoten).</li><li>Einfache Montage: schmaler D\u00fcbelrand verhindert das Tieferrutschen ins Bohrloch.</li><li>Bestm\u00f6gliche R\u00fcckmeldung des D\u00fcbels - man sp\u00fcrt, dass der D\u00fcbel perfekt sitzt.</li></ul>"}, {"Key": "KAT_VORTEILNUTZEN", "Value": "<div class=\"h10\">Vorteile</div><ul><li>Zwei Materialkomponenten f\u00fcr beste Lastwerte und intelligente Funktionen je nach Untergrund.</li><li>Bestm\u00f6gliche R\u00fcckmeldung (Feelgood-Faktor) des D\u00fcbels. Man sp\u00fcrt wenn der D\u00fcbel perfekt sitzt.</li><li>Der schmale D\u00fcbelrand verhindert das Durchrutschen ins Bohrloch.</li><li>Die ausgepr\u00e4gte Mitdrehsicherung verhindert das Mitdrehen des D\u00fcbels.</li><li>Die Europ\u00e4isch Technische Bewertung (ETA) garantiert gepr\u00fcfte Sicherheit bei sicherheitsrelevanten Anwendungen in Beton (siehe Lasttabelle).</li></ul>"}, {"Key": "KAT_FUNKTION", "Value": "<div class=\"h10\">Funktionsweise / Montage</div><ul><li>Der DuoPower ist geeignet f\u00fcr die Vorsteck- und Durchsteckmontage.</li><li>Die Expansionsfl\u00fcgel der roten Komponente unterst\u00fctzen die sichere Verspreizung und bieten zus\u00e4tzliche Sicherheit zur grauen Komponente.</li><li>Das Duo aus zwei Materialien und mehrfachen Funktionsprinzipien (klappen, spreizen, knoten) erm\u00f6glicht die Erweiterung des Anwendungsspektrums in zus\u00e4tzlichen Baustoffen mit maximalen Lasten.</li><li>Die erforderliche Schraubenl\u00e4nge ergibt sich aus D\u00fcbell\u00e4nge + Anbauteildicke +1 x Schraubendurchmesser.</li><li>Geeignet f\u00fcr Holz-, Spanplatten- sowie Stockschrauben.</li><li>Bei Plattenbaustoffen darf der gewindelose Teil der Schraube nicht l\u00e4nger als das Anbauteil sein.</li><li>Der fischer DuoPower ETA 10x50 mit Sicherheitsschraube ist zugelassen f\u00fcr Beton und Mauerwerk. Die DuoPower ETA 8x40 mit FPF II und Sicherheitsschraube sind zugelassen f\u00fcr Beton.</li></ul>"}, {"Key": "DOKBSTTOPFEATURE", "Value": "Kombination aus zwei Materialkomponenten f\u00fcr mehr Leistung."}, {"Key": "DOKBSTTOPFEATURE", "Value": "Sichere Funktionen f\u00fcr Voll- (Spreizen) und Loch- und Plattenbaustoffe (Klappen/Knoten)."}, {"Key": "DOKBSTTOPFEATURE", "Value": "Einfache Montage: schmaler D\u00fcbelrand verhindert das Tieferrutschen ins Bohrloch."}, {"Key": "DOKBSTTOPFEATURE", "Value": "Bestm\u00f6gliche R\u00fcckmeldung des D\u00fcbels - man sp\u00fcrt, dass der D\u00fcbel perfekt sitzt."}], "Attributes": [{"AttributeKey": "ZULASSUNG_E", "AttributeName": "ETA-Zulassung", "Value": "relevant"}, {"AttributeKey": "BOHRERNENNDM", "AttributeName": "Bohrernenndurchmesser", "Unit": "[mm]", "Value": "8", "TechnicalName": "<div class=\"h6\">d<sub>0</sub></div>"}, {"AttributeKey": "MIN_BOHRLT", "AttributeName": "Min. Bohrlochtiefe", "Unit": "[mm]", "Value": "76", "TechnicalName": "<div class=\"h6\">h<sub>1</sub></div>"}, {"AttributeKey": "MIN_EINSCH", "AttributeName": "Min. Einschraubtiefe", "Unit": "[mm]", "Value": "46", "TechnicalName": "<div class=\"h6\">l<sub>E,min</sub></div>"}, {"AttributeKey": "DUEBELL", "AttributeName": "D\u00fcbell\u00e4nge", "Unit": "[mm]", "Value": "40", "TechnicalName": "<div class=\"h6\">l</div>"}, {"AttributeKey": "MIN_VERAN", "AttributeName": "Min. Verankerungstiefe", "Unit": "[mm]", "Value": "40", "TechnicalName": "<div class=\"h6\">h<sub>ef</sub></div>"}, {"AttributeKey": "MAX_NUTZLG", "AttributeName": "Max. Dicke des Anbauteils", "Unit": "[mm]", "Value": "20", "TechnicalName": "<div class=\"h6\">t <sub>fix</sub></div>"}, {"AttributeKey": "SCHR_ABMG", "AttributeName": "Schraubenabmessung", "Unit": "[mm]", "Value": "6,0 x 66,5", "TechnicalName": "<div class=\"h6\">d<sub>s</sub> x l<sub>s</sub></div>"}, {"AttributeKey": "ANTRIEB", "AttributeName": "Antrieb", "Value": "TX30 / SW 10"}, {"AttributeKey": "MENGE", "AttributeName": "Menge", "Unit": "[St\u00fcck]", "Value": "50"}, {"AttributeKey": "FA_VERPACKVAR", "AttributeName": "Verpackungsvariante", "Value": "Faltschachtel"}, {"AttributeKey": "EAN_CODE", "AttributeName": "GTIN (EAN-Code)", "Value": "4048962463408"}], "FilterAttributes": [{"FilterId": "Verpackungsvariante_A", "FilterName": "Verpackungsvariante", "ValueList": ["Faltschachtel"], "Attributes": [{"AttributeKey": "DATATYPE", "AttributeName": "Suchfeld Datentyp", "Value": "A", "ValueList": ["A"]}]}, {"FilterId": "Ausf\u00fchrung_A", "FilterName": "Ausf\u00fchrung", "ValueList": ["mit Schraube"], "Attributes": [{"AttributeKey": "DATATYPE", "AttributeName": "Suchfeld Datentyp", "Value": "A", "ValueList": ["A"]}]}, {"FilterId": "D\u00fcbell\u00e4nge_N", "FilterName": "D\u00fcbell\u00e4nge", "Unit": "[mm]", "Value": "40", "Attributes": [{"AttributeKey": "DATATYPE", "AttributeName": "Suchfeld Datentyp", "Value": "N", "ValueList": ["N"]}]}, {"FilterId": "Profi / DIY_A", "FilterName": "Profi / DIY", "ValueList": ["Profi"], "Attributes": [{"AttributeKey": "DATATYPE", "AttributeName": "Suchfeld Datentyp", "Value": "A", "ValueList": ["A"]}]}, {"FilterId": "Bohrernenndurchmesser_N", "FilterName": "Bohrernenn&shy;durchmesser", "Unit": "[mm]", "Value": "8", "Attributes": [{"AttributeKey": "DATATYPE", "AttributeName": "Suchfeld Datentyp", "Value": "N", "ValueList": ["N"]}]}, {"FilterId": "Baustoff_A", "FilterName": "Baustoff", "ValueList": ["ungerissener Beton"], "Attributes": [{"AttributeKey": "DATATYPE", "AttributeName": "Suchfeld Datentyp", "Value": "A", "ValueList": ["A"]}]}, {"FilterId": "Antrieb_A", "FilterName": "Antrieb", "ValueList": ["Innenstern TX / Sechskant"], "Attributes": [{"AttributeKey": "DATATYPE", "AttributeName": "Suchfeld Datentyp", "Value": "A", "ValueList": ["A"]}]}, {"FilterId": "Max. Dicke des Anbauteils_A", "FilterName": "Max. Dicke des Anbauteils", "ValueList": ["20"], "Unit": "[mm]", "Attributes": [{"AttributeKey": "DATATYPE", "AttributeName": "Suchfeld Datentyp", "Value": "A", "ValueList": ["A"]}]}]}