{"ProductId": "060196", "ETag": "f8e18f4a1102227636c56e4d6bb6728606e666e2d16098248e3d2c357d768f81", "ProductName": "AM 30", "Slug": "/elektro-befestigungen/montage-von-rohrleitungen/metallschellen/schraubabstandsschelle-am-amd/60196-am-30", "ParentCategory": "1001342452", "ParentCategoryList": ["1001342452"], "RootCategory": "1001342438", "CategoryPath": ["1001342438", "1001342440", "1001342450", "1001342452"], "Media": [{"DocumentId": "400d5fa7dc5b41f9281cb802cf4ce5d1", "Url": "https://media.fischer.group/v7/_pim-media-prod_/Product%20Pictures/Product%20Pictures%20fischer/W1_P_P_AM-CGI_F_SALL_AQQ_V2.jpg", "Filename": "W1_P_P_AM-CGI_F_SALL_AQQ_V2.jpg", "NameConvention": "P_P_F", "OutputType": "PR", "Format": "jpg", "FileSize": 583031, "Type": "Product Picture", "Position": 1, "TextList": [{"Key": "BILDLEG_NEXMART", "Value": "Produktbild"}, {"Key": "KAT_NEU_PRODBILD", "Value": "Produktbild"}]}, {"DocumentId": "dc665b3e736823f1b02798fae7063bdf", "Url": "https://media.fischer.group/v7/_pim-media-prod_/Product%20Pictures/Product%20Pictures%20fischer/W1_P_P_AM-CGI_F_SALL_AQQ_V2.jpg?w=1000&h=1000&func=fit&bg_colour=white", "Filename": "W1_P_P_AM-CGI_F_SALL_AQQ_V2.jpg", "NameConvention": "P_P_F", "OutputType": "PP", "Format": "jpg", "FileSize": 583031, "Type": "Product Picture", "Position": 1, "TextList": [{"Key": "BILDLEG_NEXMART", "Value": "Produktbild"}, {"Key": "KAT_NEU_PRODBILD", "Value": "Produktbild"}]}, {"DocumentId": "e63ec9f1fce5e34eba316694eabf471d", "Url": "https://media.fischer.group/v7/_pim-media-prod_/Product%20Pictures/Product%20Pictures%20fischer/W1_P_P_AM-CGI_F_SALL_AQQ_V2.jpg?w=300&h=300&func=fit&bg_colour=white", "Filename": "W1_P_P_AM-CGI_F_SALL_AQQ_V2.jpg", "NameConvention": "P_P_F", "OutputType": "IS", "Format": "jpg", "FileSize": 583031, "Type": "Product Picture", "Position": 1, "TextList": [{"Key": "BILDLEG_NEXMART", "Value": "Produktbild"}, {"Key": "KAT_NEU_PRODBILD", "Value": "Produktbild"}]}, {"DocumentId": "ac4cc90beab0e2447265b83248fa3b3a", "Url": "https://media.fischer.group/v7/_pim-media-prod_/Application%20Pictures/Application%20Pictures%20CGI%20new%20CD/W1_A_I_04_214-STAHLPANZERROHR_SALL_AQQ_V1.jpg", "Filename": "W1_A_I_04_214-STAHLPANZERROHR_SALL_AQQ_V1.jpg", "NameConvention": "A_I_01", "OutputType": "PR", "Format": "jpg", "FileSize": 1403367, "Type": "Application Picture", "Position": 1, "TextList": [{"Key": "BILDLEG_NEXMART", "Value": "Anwendungsbild"}, {"Key": "KAT_NEU_PRODBILD", "Value": "Anwendungsbild"}]}, {"DocumentId": "66bdb134efb5899d16b3151dab1de66b", "Url": "https://media.fischer.group/v7/_pim-media-prod_/Application%20Pictures/Application%20Pictures%20CGI%20new%20CD/W1_A_I_04_214-STAHLPANZERROHR_SALL_AQQ_V1.jpg?w=1250&bg_colour=white", "Filename": "W1_A_I_04_214-STAHLPANZERROHR_SALL_AQQ_V1.jpg", "NameConvention": "A_I_01", "OutputType": "PP", "Format": "jpg", "FileSize": 1403367, "Type": "Application Picture", "Position": 1, "TextList": [{"Key": "BILDLEG_NEXMART", "Value": "Anwendungsbild"}, {"Key": "KAT_NEU_PRODBILD", "Value": "Anwendungsbild"}]}, {"DocumentId": "cb64ee170e583a6c17cc2356741cea7a", "Url": "https://media.fischer.group/v7/_pim-media-prod_/Application%20Pictures/Application%20Pictures%20CGI%20new%20CD/W1_A_I_04_320-BEFESTIGUNG-VON-LEITUNGEN_SALL_AQQ_V1.jpg", "Filename": "W1_A_I_04_320-BEFESTIGUNG-VON-LEITUNGEN_SALL_AQQ_V1.jpg", "NameConvention": "A_I_01", "OutputType": "PR", "Format": "jpg", "FileSize": 1852739, "Type": "Application Picture", "Position": 2, "TextList": [{"Key": "BILDLEG_NEXMART", "Value": "Anwendungsbild"}, {"Key": "KAT_NEU_PRODBILD", "Value": "Anwendungsbild"}]}, {"DocumentId": "01ff7a75d55adfbb9851840b166d7192", "Url": "https://media.fischer.group/v7/_pim-media-prod_/Application%20Pictures/Application%20Pictures%20CGI%20new%20CD/W1_A_I_04_320-BEFESTIGUNG-VON-LEITUNGEN_SALL_AQQ_V1.jpg?w=1250&bg_colour=white", "Filename": "W1_A_I_04_320-BEFESTIGUNG-VON-LEITUNGEN_SALL_AQQ_V1.jpg", "NameConvention": "A_I_01", "OutputType": "PP", "Format": "jpg", "FileSize": 1852739, "Type": "Application Picture", "Position": 2, "TextList": [{"Key": "BILDLEG_NEXMART", "Value": "Anwendungsbild"}, {"Key": "KAT_NEU_PRODBILD", "Value": "Anwendungsbild"}]}, {"DocumentId": "5af07cc0c966f75ef4f7244002c5ab3d", "Url": "https://media.fischer.group/v7/_pim-media-prod_/Application%20Pictures/Application%20Pictures%20CGI%20new%20CD/W7_PF_Z_01_AM_F_SALL_AQQ_V1.jpg", "Filename": "W7_PF_Z_01_AM_F_SALL_AQQ_V1.jpg", "NameConvention": "PF_S_01_F", "OutputType": "PR", "Format": "jpg", "FileSize": 66725, "Type": "Technical Drawing", "Position": 1, "TextList": [{"Key": "BILDLEG_NEXMART", "Value": "Technische Zeichnung"}, {"Key": "KAT_NEU_PRODBILD", "Value": "Technische Zeichnung"}]}, {"DocumentId": "7c242878a8c9b2d2b3cf56a6ed45e8df", "Url": "https://media.fischer.group/v7/_pim-media-prod_/Installation%20Drawings/Installation%20Drawings%20Family%20new%20CD/W7_PF_Z_01_AM_F_SALL_AQQ_V1.jpg?w=400&func=fit&bg_colour=white", "Filename": "W7_PF_Z_01_AM_F_SALL_AQQ_V1.jpg", "NameConvention": "PF_S_01_F", "OutputType": "PP", "Format": "jpg", "FileSize": 66725, "Type": "Technical Drawing", "Position": 1, "TextList": [{"Key": "BILDLEG_NEXMART", "Value": "Technische Zeichnung"}, {"Key": "KAT_NEU_PRODBILD", "Value": "Technische Zeichnung"}]}], "AssemblyMedia": [{"Name": "Mounting Strip 1 Picture", "Media": [{"DocumentId": "68ea1d0bd462805379638a8e536dfa56", "Url": "https://media.fischer.group/v7/_pim-media-prod_/Mounting%20Pictures/Mounting%20Pictures%20NEW/fischer/W6_M_L_01_AM_F_SALL_AQQ_V1.jpg", "Filename": "W6_M_L_01_AM_F_SALL_AQQ_V1.jpg", "NameConvention": "M_G_01_F", "OutputType": "PR", "Format": "jpg", "FileSize": 131739, "Type": "Mounting Strip 1 Picture", "Position": 1, "TextList": [{"Key": "BILDLEG_NEXMART", "Value": "Montagebild"}, {"Key": "KAT_NEU_PRODBILD", "Value": "Montagebild"}]}, {"DocumentId": "215e7f62d8d72dd0ed5c22f9b04ef572", "Url": "https://media.fischer.group/v7/_pim-media-prod_/Mounting%20Pictures/Mounting%20Pictures%20NEW/fischer/W6_M_L_01_AM_F_SALL_AQQ_V1.jpg?w=276&h=210&func=fit&bg_colour=white", "Filename": "W6_M_L_01_AM_F_SALL_AQQ_V1.jpg", "NameConvention": "M_G_01_F", "OutputType": "PP", "Format": "jpg", "FileSize": 131739, "Type": "Mounting Strip 1 Picture", "Position": 1, "TextList": [{"Key": "BILDLEG_NEXMART", "Value": "Montagebild"}, {"Key": "KAT_NEU_PRODBILD", "Value": "Montagebild"}]}, {"DocumentId": "ca3831d9cb7e6dd3ab8943f90491feff", "Url": "https://media.fischer.group/v7/_pim-media-prod_/Mounting%20Pictures/Mounting%20Pictures%20NEW/fischer/W6_M_L_02_AM_F_SALL_AQQ_V1.jpg", "Filename": "W6_M_L_02_AM_F_SALL_AQQ_V1.jpg", "NameConvention": "M_G_01_F", "OutputType": "PR", "Format": "jpg", "FileSize": 127595, "Type": "Mounting Strip 1 Picture", "Position": 2, "TextList": [{"Key": "BILDLEG_NEXMART", "Value": "Montagebild"}, {"Key": "KAT_NEU_PRODBILD", "Value": "Montagebild"}]}, {"DocumentId": "1b3609406c2b602a8db2921318071748", "Url": "https://media.fischer.group/v7/_pim-media-prod_/Mounting%20Pictures/Mounting%20Pictures%20NEW/fischer/W6_M_L_02_AM_F_SALL_AQQ_V1.jpg?w=276&h=210&func=fit&bg_colour=white", "Filename": "W6_M_L_02_AM_F_SALL_AQQ_V1.jpg", "NameConvention": "M_G_01_F", "OutputType": "PP", "Format": "jpg", "FileSize": 127595, "Type": "Mounting Strip 1 Picture", "Position": 2, "TextList": [{"Key": "BILDLEG_NEXMART", "Value": "Montagebild"}, {"Key": "KAT_NEU_PRODBILD", "Value": "Montagebild"}]}, {"DocumentId": "e602de77640f6206d96e204592f3bed4", "Url": "https://media.fischer.group/v7/_pim-media-prod_/Mounting%20Pictures/Mounting%20Pictures%20NEW/fischer/W6_M_L_03_AM_F_SALL_AQQ_V1.jpg", "Filename": "W6_M_L_03_AM_F_SALL_AQQ_V1.jpg", "NameConvention": "M_G_01_F", "OutputType": "PR", "Format": "jpg", "FileSize": 134480, "Type": "Mounting Strip 1 Picture", "Position": 3, "TextList": [{"Key": "BILDLEG_NEXMART", "Value": "Montagebild"}, {"Key": "KAT_NEU_PRODBILD", "Value": "Montagebild"}]}, {"DocumentId": "1221c022ec83ea6c3e5f9e8d61d3d5cb", "Url": "https://media.fischer.group/v7/_pim-media-prod_/Mounting%20Pictures/Mounting%20Pictures%20NEW/fischer/W6_M_L_03_AM_F_SALL_AQQ_V1.jpg?w=276&h=210&func=fit&bg_colour=white", "Filename": "W6_M_L_03_AM_F_SALL_AQQ_V1.jpg", "NameConvention": "M_G_01_F", "OutputType": "PP", "Format": "jpg", "FileSize": 134480, "Type": "Mounting Strip 1 Picture", "Position": 3, "TextList": [{"Key": "BILDLEG_NEXMART", "Value": "Montagebild"}, {"Key": "KAT_NEU_PRODBILD", "Value": "Montagebild"}]}, {"DocumentId": "3a28cde552ae62aa64fb487e41efb6f3", "Url": "https://media.fischer.group/v7/_pim-media-prod_/Mounting%20Pictures/Mounting%20Pictures%20NEW/fischer/W6_M_L_04_AM_F_SALL_AQQ_V1.jpg", "Filename": "W6_M_L_04_AM_F_SALL_AQQ_V1.jpg", "NameConvention": "M_G_01_F", "OutputType": "PR", "Format": "jpg", "FileSize": 137084, "Type": "Mounting Strip 1 Picture", "Position": 4, "TextList": [{"Key": "BILDLEG_NEXMART", "Value": "Montagebild"}, {"Key": "KAT_NEU_PRODBILD", "Value": "Montagebild"}]}, {"DocumentId": "ffcc85fddeb900582ea7958b499f1ec9", "Url": "https://media.fischer.group/v7/_pim-media-prod_/Mounting%20Pictures/Mounting%20Pictures%20NEW/fischer/W6_M_L_04_AM_F_SALL_AQQ_V1.jpg?w=276&h=210&func=fit&bg_colour=white", "Filename": "W6_M_L_04_AM_F_SALL_AQQ_V1.jpg", "NameConvention": "M_G_01_F", "OutputType": "PP", "Format": "jpg", "FileSize": 137084, "Type": "Mounting Strip 1 Picture", "Position": 4, "TextList": [{"Key": "BILDLEG_NEXMART", "Value": "Montagebild"}, {"Key": "KAT_NEU_PRODBILD", "Value": "Montagebild"}]}, {"DocumentId": "658dffb92d3afaade0e5c5c14cf29846", "Url": "https://media.fischer.group/v7/_pim-media-prod_/Mounting%20Pictures/Mounting%20Pictures%20NEW/fischer/W6_M_L_05_AM_F_SALL_AQQ_V1.jpg", "Filename": "W6_M_L_05_AM_F_SALL_AQQ_V1.jpg", "NameConvention": "M_G_01_F", "OutputType": "PR", "Format": "jpg", "FileSize": 142619, "Type": "Mounting Strip 1 Picture", "Position": 5, "TextList": [{"Key": "BILDLEG_NEXMART", "Value": "Montagebild"}, {"Key": "KAT_NEU_PRODBILD", "Value": "Montagebild"}]}, {"DocumentId": "9a6bc933cb1f1d0ad0501e7fc98cc051", "Url": "https://media.fischer.group/v7/_pim-media-prod_/Mounting%20Pictures/Mounting%20Pictures%20NEW/fischer/W6_M_L_05_AM_F_SALL_AQQ_V1.jpg?w=276&h=210&func=fit&bg_colour=white", "Filename": "W6_M_L_05_AM_F_SALL_AQQ_V1.jpg", "NameConvention": "M_G_01_F", "OutputType": "PP", "Format": "jpg", "FileSize": 142619, "Type": "Mounting Strip 1 Picture", "Position": 5, "TextList": [{"Key": "BILDLEG_NEXMART", "Value": "Montagebild"}, {"Key": "KAT_NEU_PRODBILD", "Value": "Montagebild"}]}]}], "TextList": [{"Key": "BEZEICHNUNG", "Value": "AM 30"}, {"Key": "ARTIKELLANG", "Value": "AM 30"}, {"Key": "ECOMLANG", "Value": "fischer Schraubabstandsschelle Metall AM 30"}, {"Key": "DOKBSTMARKCLAIM", "Value": "Die montagefreundliche Metall-Abstandsschelle f\u00fcr Kabel und Rohre."}, {"Key": "DOKBSTMARKDESCR", "Value": "Die fischer Schraubabstandsschelle Metall AM ist eine montagefreundliche L\u00f6sung zur Befestigung von Stahlpanzerrohren und Elektrokabeln. Die Metallschelle mit Gewinde kann mit dem fischer Nagelanker FNA II 6 x 30 M 6 x 41 und wahlweise mit den Stockschrauben STST 6 x 60 und STST 6 x 80 in Beton, Vollstein und Spannbeton-Hohlplatten befestigt werden. Mit dem fischer Nageld\u00fcbel N 6 x 40 / 10 M 6 h\u00e4lt die Abstandsschelle sicher in Beton, aber auch in Vollstein, Mauerziegel und Leichtbeton."}, {"Key": "KAT_POS", "Value": "<div class=\"h9\">Die montagefreundliche Metall-Abstandsschelle f\u00fcr Kabel und Rohre."}, {"Key": "KAT_ANWENDUNG_GEN", "Value": "<div class=\"h10\">Anwendungen</div><strong>Zur Befestigung von:</strong><ul><li>Stahlpanzerrohren</li><li>Elektrokabeln</li><li>Kupfer- und Metallrohren</li></ul>"}, {"Key": "KAT_BAUSTOFF_GEN", "Value": "<div class=\"h10\">Baustoffe</div><strong>Bei Verwendung von Nagelanker FNA II:</strong><ul><li>Beton</li><li>Kalksand-Vollstein</li><li>Naturstein mit dichtem Gef\u00fcge</li><li>Spannbeton-Hohlplatten</li></ul><strong>Bei Verwendung von Nageld\u00fcbel N:</strong><ul><li>Beton</li><li>Kalksand-Vollstein</li><li>Mauerziegel</li><li>Naturstein</li><li>Vollstein aus Leichtbeton</li></ul>"}, {"Key": "POCTOPFEATURESGEN", "Value": "<div class=\"h10\">Top Features</div><ul><li>Schnelle Montage durch Schnellverschlussb\u00fcgel.</li><li>Vormontierte Kombischraube mit Schlitz- und Kreuzschlitzaufnahme.</li><li>Hohe Flexibilit\u00e4t: Montage mit fischer Nagelanker FNA II oder Nageld\u00fcbel N 6.</li></ul>"}, {"Key": "KAT_VORTEILNUTZEN", "Value": "<div class=\"h10\">Vorteile</div><ul><li>Der Schnellverschlussb\u00fcgel sorgt f\u00fcr ein leichtes \u00d6ffnen und Schlie\u00dfen ohne vollst\u00e4ndiges Ausdrehen der Schraube und erlaubt eine einfache und schnelle Montage.</li><li>Die vormontierte Kombischraube mit g\u00e4ngiger Schlitz- und Kreuzschlitz-Aufnahme erlaubt die Verwendung unterschiedlicher Schraubendreher und erm\u00f6glicht dadurch eine unkomplizierte Installation.</li></ul>"}, {"Key": "KAT_FUNKTION", "Value": "<div class=\"h10\">Funktionsweise / Montage</div><ul><li>Die Schraubabstandsschelle AM mit M6 Gewinde kann wahlweise mit fischer Nagelanker FNA II 6x30 M6x41, Stockschraube STST 6x60 oder STST 6x80 oder Nageld\u00fcbel N 6x40/10 M6 befestigt werden.</li></ul>"}, {"Key": "DOKBSTTOPFEATURE", "Value": "Schnelle Montage durch Schnellverschlussb\u00fcgel."}, {"Key": "DOKBSTTOPFEATURE", "Value": "Vormontierte Kombischraube mit Schlitz- und Kreuzschlitzaufnahme."}, {"Key": "DOKBSTTOPFEATURE", "Value": "Hohe Flexibilit\u00e4t: Montage mit fischer Nagelanker FNA II oder Nageld\u00fcbel N 6."}], "Attributes": [{"AttributeKey": "SPANNBER", "AttributeName": "Spannbereich", "Unit": "[mm]", "Value": "30 - 31", "TechnicalName": "<div class=\"h6\">D</div>"}, {"AttributeKey": "MENGE", "AttributeName": "Menge", "Unit": "[St\u00fcck]", "Value": "50"}, {"AttributeKey": "EAN_CODE", "AttributeName": "GTIN (EAN-Code)", "Value": "4006209601969"}], "FilterAttributes": [{"FilterId": "Material_A", "FilterName": "Material", "ValueList": ["galvanisch verzinkter Stahl"], "Attributes": [{"AttributeKey": "DATATYPE", "AttributeName": "Suchfeld Datentyp", "Value": "A", "ValueList": ["A"]}]}, {"FilterId": "Profi / DIY_A", "FilterName": "Profi / DIY", "ValueList": ["Profi"], "Attributes": [{"AttributeKey": "DATATYPE", "AttributeName": "Suchfeld Datentyp", "Value": "A", "ValueList": ["A"]}]}]}